emobject/__init__.py
emobject/core.py
emobject/emexperiment.py
emobject/emimage.py
emobject/emlayer.py
emobject/emobject.py
emobject/empublicaccess.py
emobject/emroitools.py
emobject/errors.py
emobject/version.py
emobject/utils/__init__.py
emobject/utils/graph.py
emobject/utils/helpers.py
emobject/utils/io.py
emobject/utils/visualization.py
emobject-0.9.0.dist-info/LICENSE
emobject-0.9.0.dist-info/METADATA
emobject-0.9.0.dist-info/WHEEL
emobject-0.9.0.dist-info/top_level.txt
emobject-0.9.0.dist-info/RECORD
