Metadata-Version: 2.1
Name: emobject
Version: 0.9.0
Summary: data abstraction and libraries for spatial omics
Home-page: https://docs.enablemedicine.com/emobject/
Author: Ethan A. G. Baker
Author-email: ethan.baker@enablemedicine.com
License: UNKNOWN
Project-URL: Documentation, https://docs.enablemedicine.com/emobject/
Project-URL: Source, https://gitlab.com/enable-medicine-public/emobject/
Platform: UNKNOWN
Requires-Python: >=3.7, <4
License-File: LICENSE
Requires-Dist: numpy
Requires-Dist: jupyter
Requires-Dist: pandas
Requires-Dist: zarr
Requires-Dist: matplotlib
Requires-Dist: scipy
Requires-Dist: scikit-image
Requires-Dist: zstandard
Requires-Dist: python-dotenv
Requires-Dist: networkx
Requires-Dist: anndata
Requires-Dist: opencv-python
Requires-Dist: pyyaml
Requires-Dist: ome-types
Requires-Dist: tifffile
Requires-Dist: opencv-python-headless
Requires-Dist: openpyxl
Requires-Dist: seaborn
Requires-Dist: requests
Requires-Dist: boto3
Requires-Dist: emoaccess >=0.20.0
Requires-Dist: lxml
Provides-Extra: dev
Requires-Dist: pdoc3 ; extra == 'dev'
Requires-Dist: flake8 ; extra == 'dev'
Requires-Dist: pytest ; extra == 'dev'
Requires-Dist: pytest-cov ; extra == 'dev'
Requires-Dist: pytest-xdist ; extra == 'dev'
